pozansky_stock_analysis/__init__.py
pozansky_stock_analysis/__main__.py
pozansky_stock_analysis/candlestick_patterns.py
pozansky_stock_analysis/chart_patterns.py
pozansky_stock_analysis/server.py
pozansky_stock_analysis/technical_indicators.py
pozansky_stock_analysis/test.py
pozansky_stock_analysis/test2.py
pozansky_stock_analysis/test_images/000001.SS_1d_chart.png
pozansky_stock_analysis/test_images/0700.HK_1d_chart.png
pozansky_stock_analysis/test_images/0700.HK_4h_chart.png
pozansky_stock_analysis/test_images/AAPL_1d_chart.png
pozansky_stock_analysis/test_images/AAPL_1h_chart.png
pozansky_stock_analysis/test_images/AAPL_1wk_chart.png
pozansky_stock_analysis/test_images/AAPL_4h_chart.png
pozansky_stock_analysis/test_images/AMZN_1d_chart.png
pozansky_stock_analysis/test_images/BABA_1d_chart.png
pozansky_stock_analysis/test_images/GOOGL_1d_chart.png
pozansky_stock_analysis/test_images/MSFT_1d_chart.png
pozansky_stock_analysis/test_images/NVDA_1d_chart.png
pozansky_stock_analysis/test_images/TSLA_1d_chart.png
pozansky_stock_analysis/test_images/^GSPC_1d_chart.png
pozansky_stock_analysis-1.4.0.dist-info/METADATA
pozansky_stock_analysis-1.4.0.dist-info/WHEEL
pozansky_stock_analysis-1.4.0.dist-info/entry_points.txt
pozansky_stock_analysis-1.4.0.dist-info/RECORD
